btmhdw/__init__.py
btmhdw/btmhdw.py
btmhdw/ed25519.py
btmhdw/key.py
btmhdw/segwit.py
btmhdw/transaction.py
btmhdw/utils.py
btmhdw-2.2.2.dist-info/LICENSE
btmhdw-2.2.2.dist-info/METADATA
btmhdw-2.2.2.dist-info/WHEEL
btmhdw-2.2.2.dist-info/top_level.txt
btmhdw-2.2.2.dist-info/RECORD
