Metadata-Version: 2.1
Name: btmhdw
Version: 2.2.2
Summary: The implementation of Hierarchical Deterministic (HD) wallets generator for Bytom blockchain
Home-page: https://github.com/meherett/btmhdw
Author: Meheret Tesfaye
Author-email: meherett@zoho.com
License: MIT
Platform: UNKNOWN
Classifier: Development Status :: 3 - Alpha
Classifier: License :: OSI Approved :: MIT License
Classifier: Programming Language :: Python :: 3.5
Classifier: Programming Language :: Python :: 3.6
Classifier: Programming Language :: Python :: 3.7
Classifier: Programming Language :: Python :: 3.8
Requires-Python: >=3.5,<4
Requires-Dist: mnemonic (<1,>=0.19)
Requires-Dist: ed25519 (<2,>=1.5)
